immutable/__init__.py
immutable/_version.py
immutable/main.py
immutable/py.typed
python_immutable-1.2.2.dist-info/METADATA
python_immutable-1.2.2.dist-info/WHEEL
python_immutable-1.2.2.dist-info/licenses/LICENSE
python_immutable-1.2.2.dist-info/RECORD
