Metadata-Version: 2.4
Name: python-immutable
Version: 1.2.2
Summary: Immutable implementation for Python using dataclasses
Author-email: Sassan Haradji <me@sassanh.com>
Maintainer-email: Sassan Haradji <me@sassanh.com>
License: Apache-2.0
License-File: LICENSE
Keywords: dataclass,frozen,immutable,python,typing
Requires-Python: >=3.9
